NiukeRenliziyuanGangQiuzhiJingyanFenxiang20212022Fix1/README.md
NiukeRenliziyuanGangQiuzhiJingyanFenxiang20212022Fix1/__init__.py
NiukeRenliziyuanGangQiuzhiJingyanFenxiang20212022Fix1/__main__.py
NiukeRenliziyuanGangQiuzhiJingyanFenxiang20212022Fix1/file.epub
NiukeRenliziyuanGangQiuzhiJingyanFenxiang20212022Fix1/index.html
NiukeRenliziyuanGangQiuzhiJingyanFenxiang20212022Fix1/css/__init__.py
NiukeRenliziyuanGangQiuzhiJingyanFenxiang20212022Fix1/css/annotations.css
NiukeRenliziyuanGangQiuzhiJingyanFenxiang20212022Fix1/css/main.css
NiukeRenliziyuanGangQiuzhiJingyanFenxiang20212022Fix1/css/normalize.css
NiukeRenliziyuanGangQiuzhiJingyanFenxiang20212022Fix1/css/popup.css
NiukeRenliziyuanGangQiuzhiJingyanFenxiang20212022Fix1/font/__init__.py
NiukeRenliziyuanGangQiuzhiJingyanFenxiang20212022Fix1/font/fontello.eot
NiukeRenliziyuanGangQiuzhiJingyanFenxiang20212022Fix1/font/fontello.svg
NiukeRenliziyuanGangQiuzhiJingyanFenxiang20212022Fix1/font/fontello.ttf
NiukeRenliziyuanGangQiuzhiJingyanFenxiang20212022Fix1/font/fontello.woff
NiukeRenliziyuanGangQiuzhiJingyanFenxiang20212022Fix1/img/__init__.py
NiukeRenliziyuanGangQiuzhiJingyanFenxiang20212022Fix1/img/annotator-glyph-sprite.png
NiukeRenliziyuanGangQiuzhiJingyanFenxiang20212022Fix1/img/annotator-icon-sprite.png
NiukeRenliziyuanGangQiuzhiJingyanFenxiang20212022Fix1/img/apple-touch-icon.png
NiukeRenliziyuanGangQiuzhiJingyanFenxiang20212022Fix1/img/cancelfullscreen.png
NiukeRenliziyuanGangQiuzhiJingyanFenxiang20212022Fix1/img/close.png
NiukeRenliziyuanGangQiuzhiJingyanFenxiang20212022Fix1/img/fullscreen.png
NiukeRenliziyuanGangQiuzhiJingyanFenxiang20212022Fix1/img/loader.gif
NiukeRenliziyuanGangQiuzhiJingyanFenxiang20212022Fix1/img/menu-icon.png
NiukeRenliziyuanGangQiuzhiJingyanFenxiang20212022Fix1/img/save.png
NiukeRenliziyuanGangQiuzhiJingyanFenxiang20212022Fix1/img/saved.png
NiukeRenliziyuanGangQiuzhiJingyanFenxiang20212022Fix1/img/settings-s.png
NiukeRenliziyuanGangQiuzhiJingyanFenxiang20212022Fix1/img/settings.png
niuke_renliziyuan_gang_qiuzhi_jingyan_fenxiang_2021_2022_fix1-2025.3.25.0.dist-info/METADATA
niuke_renliziyuan_gang_qiuzhi_jingyan_fenxiang_2021_2022_fix1-2025.3.25.0.dist-info/WHEEL
niuke_renliziyuan_gang_qiuzhi_jingyan_fenxiang_2021_2022_fix1-2025.3.25.0.dist-info/entry_points.txt
niuke_renliziyuan_gang_qiuzhi_jingyan_fenxiang_2021_2022_fix1-2025.3.25.0.dist-info/top_level.txt
niuke_renliziyuan_gang_qiuzhi_jingyan_fenxiang_2021_2022_fix1-2025.3.25.0.dist-info/RECORD
